Metadata-Version: 2.2
Name: vidtoolz-apply-fadein-fadeout
Version: 0.0.1
Summary: Apply fadein-fadeout effects on videos 
Author: Sukhbinder Singh
License: Apache-2.0
Project-URL: Homepage, https://github.com/sukhbinder/vidtoolz-apply-fadein-fadeout
Project-URL: Changelog, https://github.com/sukhbinder/vidtoolz-apply-fadein-fadeout/releases
Project-URL: Issues, https://github.com/sukhbinder/vidtoolz-apply-fadein-fadeout/issues
Project-URL: CI, https://github.com/sukhbinder/vidtoolz-apply-fadein-fadeout/actions
Classifier: License :: OSI Approved :: Apache Software License
License-File: LICENSE
Requires-Dist: vidtoolz
Provides-Extra: test
Requires-Dist: pytest; extra == "test"
